{
  "css/main.css": "css/main-c926a90721.css",
  "css/vendor.css": "css/vendor-7e24774643.css",
  "fonts/AlumniSans-Medium.woff2": "fonts/AlumniSans-Medium-fbc83f524c.woff2",
  "fonts/AlumniSans-Regular.woff2": "fonts/AlumniSans-Regular-983d8c6b73.woff2",
  "fonts/AlumniSans-SemiBold.woff2": "fonts/AlumniSans-SemiBold-36c845b885.woff2",
  "fonts/HelveticaNeueCyr-Bold.woff2": "fonts/HelveticaNeueCyr-Bold-17b55fc532.woff2",
  "fonts/HelveticaNeueCyr-Light.woff2": "fonts/HelveticaNeueCyr-Light-a35e811688.woff2",
  "fonts/HelveticaNeueCyr-Medium.woff2": "fonts/HelveticaNeueCyr-Medium-cbd5d59ffb.woff2",
  "fonts/HelveticaNeueCyr-Regular.woff2": "fonts/HelveticaNeueCyr-Regular-a137f9892a.woff2",
  "img/about-img.png": "img/about-img-79361fef0f.png",
  "img/about-img.webp": "img/about-img-6ec2c310a7.webp",
  "img/bottle.svg": "img/bottle-c577f2749a.svg",
  "img/client1.png": "img/client1-51d61ff709.png",
  "img/client1.webp": "img/client1-306d085666.webp",
  "img/client2.png": "img/client2-592b828132.png",
  "img/client2.webp": "img/client2-df102e7dc8.webp",
  "img/client3.png": "img/client3-cceef74768.png",
  "img/client3.webp": "img/client3-5e11d31304.webp",
  "img/client4.png": "img/client4-ad1954b398.png",
  "img/client4.webp": "img/client4-03bab68dcd.webp",
  "img/feedback1.png": "img/feedback1-eb694fd680.png",
  "img/feedback1.webp": "img/feedback1-4a8b61d87e.webp",
  "img/feedback2.png": "img/feedback2-b984c5246c.png",
  "img/feedback2.webp": "img/feedback2-2631f3d9c2.webp",
  "img/header-decor-left.png": "img/header-decor-left-a9f257143d.png",
  "img/header-decor-left.webp": "img/header-decor-left-2e74aa1acb.webp",
  "img/header-decor-right.png": "img/header-decor-right-bc4be77d69.png",
  "img/header-decor-right.webp": "img/header-decor-right-ad92295a30.webp",
  "img/hero-bg1.png": "img/hero-bg1-4a7aa08bca.png",
  "img/hero-bg1.webp": "img/hero-bg1-e1531bc9a8.webp",
  "img/hero-bg2.png": "img/hero-bg2-293f650719.png",
  "img/hero-bg2.webp": "img/hero-bg2-1dde880ad7.webp",
  "img/hero-bg3.png": "img/hero-bg3-73f0e44b6d.png",
  "img/hero-bg3.webp": "img/hero-bg3-fb2b2a4eaa.webp",
  "img/hero-bg4.png": "img/hero-bg4-c375d69527.png",
  "img/hero-bg4.webp": "img/hero-bg4-4ce51f91f2.webp",
  "img/hero-bg5.png": "img/hero-bg5-cf06977836.png",
  "img/hero-bg5.webp": "img/hero-bg5-7525e2cec7.webp",
  "img/hero-bg6.png": "img/hero-bg6-3a2180c2c2.png",
  "img/hero-bg6.webp": "img/hero-bg6-9b5629468b.webp",
  "img/insta1.png": "img/insta1-e93ee36c32.png",
  "img/insta1.webp": "img/insta1-37835f9cfb.webp",
  "img/insta2.png": "img/insta2-5368527a59.png",
  "img/insta2.webp": "img/insta2-630231a423.webp",
  "img/insta3.png": "img/insta3-8e2ff83e96.png",
  "img/insta3.webp": "img/insta3-de919824e6.webp",
  "img/insta4.png": "img/insta4-e11e71efbf.png",
  "img/insta4.webp": "img/insta4-aa63952b0e.webp",
  "img/insta5.png": "img/insta5-5d826c2b81.png",
  "img/insta5.webp": "img/insta5-bd6e06ba11.webp",
  "img/instagram-bg.png": "img/instagram-bg-4d9274f387.png",
  "img/instagram-bg.webp": "img/instagram-bg-4523c13e8f.webp",
  "img/iphone.png": "img/iphone-2313fd8319.png",
  "img/iphone.webp": "img/iphone-c9611d1f73.webp",
  "img/location-marker.svg": "img/location-marker-f135e12236.svg",
  "img/logo.png": "img/logo-e446d8b491.png",
  "img/logo.webp": "img/logo-7ef01c29f6.webp",
  "img/map.png": "img/map-a95c439543.png",
  "img/map.webp": "img/map-6db0cb8174.webp",
  "img/modal-consultation.png": "img/modal-consultation-71dd579309.png",
  "img/modal-consultation.webp": "img/modal-consultation-d3547ad076.webp",
  "img/modal-feedback.png": "img/modal-feedback-7b4af440c1.png",
  "img/modal-feedback.webp": "img/modal-feedback-7e941e5ce8.webp",
  "img/new-product1.png": "img/new-product1-b36c1fe56d.png",
  "img/new-product1.webp": "img/new-product1-e02fe24d9a.webp",
  "img/new-product2.png": "img/new-product2-41ece8b8ba.png",
  "img/new-product2.webp": "img/new-product2-804774e189.webp",
  "img/new-product3.png": "img/new-product3-a47b3d18b2.png",
  "img/new-product3.webp": "img/new-product3-2a02b4def5.webp",
  "img/new-product4.png": "img/new-product4-6e85cccbc3.png",
  "img/new-product4.webp": "img/new-product4-3e5a087330.webp",
  "img/new-product5.png": "img/new-product5-8ad6a4a78f.png",
  "img/new-product5.webp": "img/new-product5-ab1c466bb6.webp",
  "img/our-products1.png": "img/our-products1-4922077aca.png",
  "img/our-products1.webp": "img/our-products1-243b154a95.webp",
  "img/our-products2.png": "img/our-products2-45c6bc69bd.png",
  "img/our-products2.webp": "img/our-products2-a0cc840a97.webp",
  "img/our-products3.png": "img/our-products3-ae5cd89842.png",
  "img/our-products3.webp": "img/our-products3-fda3d9bca6.webp",
  "img/our-products4.png": "img/our-products4-f5331fa949.png",
  "img/our-products4.webp": "img/our-products4-61ccecd894.webp",
  "img/our-products5.png": "img/our-products5-115252ba32.png",
  "img/our-products5.webp": "img/our-products5-8ce60e6caf.webp",
  "img/partners2.png": "img/partners2-df94674d21.png",
  "img/partners2.webp": "img/partners2-ee9bb5a853.webp",
  "img/phone.svg": "img/phone-5ba3222bda.svg",
  "img/qr.png": "img/qr-7c36ba2745.png",
  "img/qr.webp": "img/qr-b8dea8ead4.webp",
  "img/sprite.svg": "img/sprite-8428403b3e.svg",
  "img/svg/about1.svg": "img/svg/about1-c9c43ed43f.svg",
  "img/svg/about2.svg": "img/svg/about2-650bcfc112.svg",
  "img/svg/about3.svg": "img/svg/about3-4a6ee64440.svg",
  "img/svg/about4.svg": "img/svg/about4-3e04446b34.svg",
  "img/svg/barrel.svg": "img/svg/barrel-484a788ce0.svg",
  "img/svg/bottle.svg": "img/svg/bottle-0bf4380d66.svg",
  "img/svg/check.svg": "img/svg/check-89c6e5ce79.svg",
  "img/svg/clients.svg": "img/svg/clients-4a0224c357.svg",
  "img/svg/insta.svg": "img/svg/insta-bb0982f2ec.svg",
  "img/svg/lang.svg": "img/svg/lang-c446f9ac36.svg",
  "img/svg/left.svg": "img/svg/left-da4b68373a.svg",
  "img/svg/mail.svg": "img/svg/mail-3f5aef7cb8.svg",
  "img/svg/phone.svg": "img/svg/phone-4d1a12dbb3.svg",
  "img/svg/right.svg": "img/svg/right-1c2b91854d.svg",
  "img/svg/telegram.svg": "img/svg/telegram-3b638f9724.svg",
  "img/svg/whatsapp.svg": "img/svg/whatsapp-4447b5732a.svg",
  "img/user.svg": "img/user-72440b1d8b.svg",
  "js/main.js": "js/main-1900cea7ce.js"
}